[{"rect": [0, 0, 415, 415], "labels": [0], "size": 81545}, {"rect": [191, 69, 44, 44], "labels": [7], "size": 84}, {"rect": [100, 99, 9, 20], "labels": [8], "size": 30}, {"rect": [365, 110, 13, 31], "labels": [9], "size": 50}, {"rect": [98, 128, 0, 31], "labels": [11], "size": 32}, {"rect": [248, 129, 15, 4], "labels": [13], "size": 35}, {"rect": [200, 134, 50, 58], "labels": [15], "size": 319}, {"rect": [227, 157, 12, 3], "labels": [16], "size": 29}, {"rect": [347, 159, 13, 36], "labels": [17], "size": 86}, {"rect": [103, 175, 96, 95], "labels": [18], "size": 866}, {"rect": [137, 178, 18, 8], "labels": [20], "size": 23}, {"rect": [244, 182, 4, 4], "labels": [21], "size": 21}, {"rect": [361, 194, 0, 35], "labels": [22], "size": 36}, {"rect": [282, 236, 75, 75], "labels": [23], "size": 401}, {"rect": [203, 263, 8, 17], "labels": [25], "size": 25}, {"rect": [321, 272, 21, 21], "labels": [26], "size": 22}, {"rect": [231, 304, 15, 30], "labels": [27], "size": 169}, {"rect": [240, 312, 13, 23], "labels": [29], "size": 50}, {"rect": [194, 313, 89, 102], "labels": [30], "size": 1122}, {"rect": [253, 315, 27, 1], "labels": [32], "size": 46}, {"rect": [224, 327, 15, 20], "labels": [33], "size": 49}, {"rect": [210, 343, 22, 48], "labels": [34], "size": 61}, {"rect": [211, 355, 18, 40], "labels": [35], "size": 55}, {"rect": [182, 363, 31, 52], "labels": [37], "size": 933}, {"rect": [105, 377, 30, 20], "labels": [44], "size": 250}, {"rect": [114, 388, 17, 8], "labels": [47], "size": 29}, {"rect": [210, 343, 22, 52], "labels": [34, 35], "size": 116}, {"rect": [210, 327, 29, 68], "labels": [34, 35, 33], "size": 165}, {"rect": [180, 327, 59, 68], "labels": [34, 35, 33, 36], "size": 240}, {"rect": [231, 304, 22, 31], "labels": [27, 29], "size": 219}, {"rect": [180, 304, 73, 91], "labels": [27, 29, 34, 35, 33, 36], "size": 459}, {"rect": [200, 134, 50, 58], "labels": [15, 16], "size": 348}, {"rect": [200, 134, 50, 58], "labels": [15, 16, 21], "size": 369}, {"rect": [180, 304, 73, 111], "labels": [27, 29, 34, 35, 33, 36, 37], "size": 1392}, {"rect": [248, 110, 130, 85], "labels": [9, 10, 13, 17], "size": 714}, {"rect": [180, 304, 103, 111], "labels": [27, 29, 34, 35, 33, 36, 37, 30], "size": 2514}, {"rect": [180, 304, 103, 111], "labels": [27, 29, 34, 35, 33, 36, 37, 30, 32], "size": 2560}, {"rect": [103, 175, 96, 95], "labels": [18, 20], "size": 889}, {"rect": [0, 0, 415, 415], "labels": [0, 24], "size": 81618}, {"rect": [0, 0, 415, 415], "labels": [0, 24, 41, 46, 40, 45, 47, 44, 39, 38, 31, 12, 42, 43, 18, 20, 1, 9, 10, 13, 17, 5, 8, 7, 23, 15, 16, 21, 4, 22, 11, 25, 28, 27, 29, 34, 35, 33, 36, 37, 30, 32, 3, 26], "size": 101506}, {"rect": [0, 0, 415, 415], "labels": [2, 14, 6, 0, 24, 41, 46, 40, 45, 47, 44, 39, 38, 31, 12, 42, 43, 18, 20, 1, 9, 10, 13, 17, 5, 8, 7, 23, 15, 16, 21, 4, 22, 11, 25, 28, 27, 29, 34, 35, 33, 36, 37, 30, 32, 3, 26], "size": 148024}, {"rect": [0, 0, 415, 415], "labels": [2, 14, 6, 0, 24, 41, 46, 40, 45, 47, 44, 39, 38, 31, 12, 42, 43, 18, 20, 1, 9, 10, 13, 17, 5, 8, 7, 23, 15, 16, 21, 4, 22, 11, 25, 28, 27, 29, 34, 35, 33, 36, 37, 30, 32, 3, 26, 19], "size": 173056}]