[{"rect": [0, 0, 179, 173], "labels": [0], "size": 23061}, {"rect": [4, 0, 14, 9], "labels": [1], "size": 108}, {"rect": [34, 0, 28, 63], "labels": [2], "size": 334}, {"rect": [176, 0, 1, 18], "labels": [3], "size": 32}, {"rect": [178, 0, 33, 35], "labels": [4], "size": 589}, {"rect": [200, 0, 6, 5], "labels": [5], "size": 38}, {"rect": [0, 0, 345, 415], "labels": [6], "size": 36595}, {"rect": [211, 0, 204, 228], "labels": [7], "size": 14660}, {"rect": [236, 0, 5, 15], "labels": [8], "size": 51}, {"rect": [300, 0, 4, 5], "labels": [9], "size": 28}, {"rect": [214, 10, 4, 8], "labels": [10], "size": 23}, {"rect": [85, 20, 12, 5], "labels": [11], "size": 26}, {"rect": [96, 26, 7, 13], "labels": [12], "size": 28}, {"rect": [0, 29, 39, 196], "labels": [13], "size": 4107}, {"rect": [176, 32, 6, 12], "labels": [14], "size": 34}, {"rect": [291, 35, 76, 18], "labels": [15], "size": 270}, {"rect": [242, 37, 20, 10], "labels": [16], "size": 30}, {"rect": [177, 38, 220, 377], "labels": [17], "size": 56524}, {"rect": [293, 40, 82, 67], "labels": [18], "size": 3680}, {"rect": [177, 41, 6, 22], "labels": [19], "size": 57}, {"rect": [190, 44, 15, 75], "labels": [20], "size": 322}, {"rect": [341, 44, 32, 28], "labels": [21], "size": 168}, {"rect": [358, 45, 23, 17], "labels": [22], "size": 295}, {"rect": [80, 49, 6, 7], "labels": [23], "size": 37}, {"rect": [389, 54, 14, 15], "labels": [24], "size": 124}, {"rect": [192, 55, 2, 30], "labels": [25], "size": 44}, {"rect": [179, 59, 4, 10], "labels": [26], "size": 42}, {"rect": [170, 62, 5, 45], "labels": [27], "size": 111}, {"rect": [224, 69, 24, 31], "labels": [28], "size": 184}, {"rect": [66, 70, 29, 19], "labels": [29], "size": 131}, {"rect": [181, 72, 10, 30], "labels": [30], "size": 158}, {"rect": [322, 74, 79, 145], "labels": [31], "size": 1094}, {"rect": [306, 79, 12, 12], "labels": [32], "size": 86}, {"rect": [10, 85, 12, 33], "labels": [33], "size": 43}, {"rect": [293, 97, 4, 11], "labels": [34], "size": 20}, {"rect": [39, 98, 27, 69], "labels": [35], "size": 250}, {"rect": [285, 99, 11, 15], "labels": [36], "size": 63}, {"rect": [170, 101, 2, 32], "labels": [37], "size": 51}, {"rect": [321, 102, 16, 5], "labels": [38], "size": 29}, {"rect": [105, 104, 5, 13], "labels": [39], "size": 23}, {"rect": [219, 105, 7, 24], "labels": [40], "size": 81}, {"rect": [137, 107, 25, 49], "labels": [41], "size": 91}, {"rect": [256, 117, 4, 15], "labels": [42], "size": 22}, {"rect": [187, 129, 56, 60], "labels": [43], "size": 760}, {"rect": [94, 131, 13, 12], "labels": [44], "size": 78}, {"rect": [158, 132, 11, 23], "labels": [45], "size": 56}, {"rect": [124, 141, 38, 34], "labels": [46], "size": 323}, {"rect": [18, 143, 60, 61], "labels": [47], "size": 1274}, {"rect": [342, 150, 3, 17], "labels": [48], "size": 26}, {"rect": [288, 153, 9, 48], "labels": [49], "size": 384}, {"rect": [84, 157, 5, 8], "labels": [50], "size": 22}, {"rect": [175, 157, 5, 11], "labels": [51], "size": 53}, {"rect": [0, 160, 2, 30], "labels": [52], "size": 57}, {"rect": [265, 164, 17, 42], "labels": [53], "size": 407}, {"rect": [45, 172, 21, 24], "labels": [54], "size": 49}, {"rect": [119, 172, 15, 16], "labels": [55], "size": 147}, {"rect": [89, 176, 6, 25], "labels": [56], "size": 33}, {"rect": [151, 176, 10, 8], "labels": [57], "size": 46}, {"rect": [142, 184, 6, 10], "labels": [58], "size": 54}, {"rect": [132, 200, 20, 8], "labels": [59], "size": 81}, {"rect": [126, 205, 5, 13], "labels": [60], "size": 27}, {"rect": [11, 206, 11, 9], "labels": [61], "size": 59}, {"rect": [396, 207, 19, 124], "labels": [62], "size": 1878}, {"rect": [399, 209, 16, 23], "labels": [63], "size": 68}, {"rect": [129, 210, 46, 103], "labels": [64], "size": 2111}, {"rect": [155, 210, 4, 5], "labels": [65], "size": 20}, {"rect": [168, 213, 6, 13], "labels": [66], "size": 72}, {"rect": [9, 218, 5, 6], "labels": [67], "size": 23}, {"rect": [280, 221, 22, 72], "labels": [68], "size": 1128}, {"rect": [119, 230, 11, 16], "labels": [69], "size": 79}, {"rect": [169, 231, 4, 9], "labels": [70], "size": 22}, {"rect": [102, 235, 12, 23], "labels": [71], "size": 115}, {"rect": [93, 236, 4, 16], "labels": [72], "size": 33}, {"rect": [304, 240, 0, 63], "labels": [73], "size": 64}, {"rect": [119, 247, 9, 11], "labels": [74], "size": 39}, {"rect": [125, 247, 9, 15], "labels": [75], "size": 64}, {"rect": [37, 255, 4, 9], "labels": [76], "size": 31}, {"rect": [49, 256, 65, 159], "labels": [77], "size": 5954}, {"rect": [157, 264, 9, 10], "labels": [78], "size": 72}, {"rect": [0, 268, 5, 10], "labels": [79], "size": 39}, {"rect": [8, 268, 4, 6], "labels": [80], "size": 24}, {"rect": [19, 269, 4, 7], "labels": [81], "size": 25}, {"rect": [107, 270, 5, 6], "labels": [82], "size": 23}, {"rect": [400, 273, 15, 20], "labels": [83], "size": 51}, {"rect": [17, 275, 16, 24], "labels": [84], "size": 40}, {"rect": [117, 275, 6, 8], "labels": [85], "size": 33}, {"rect": [159, 275, 15, 11], "labels": [86], "size": 114}, {"rect": [1, 278, 3, 8], "labels": [87], "size": 23}, {"rect": [100, 282, 9, 7], "labels": [88], "size": 52}, {"rect": [399, 286, 7, 9], "labels": [89], "size": 33}, {"rect": [100, 288, 13, 27], "labels": [90], "size": 149}, {"rect": [138, 290, 49, 63], "labels": [91], "size": 1106}, {"rect": [132, 293, 7, 7], "labels": [92], "size": 45}, {"rect": [6, 299, 10, 20], "labels": [93], "size": 46}, {"rect": [152, 299, 7, 8], "labels": [94], "size": 27}, {"rect": [159, 303, 24, 20], "labels": [95], "size": 130}, {"rect": [105, 308, 116, 107], "labels": [96], "size": 6589}, {"rect": [139, 313, 5, 8], "labels": [97], "size": 38}, {"rect": [383, 315, 32, 100], "labels": [98], "size": 2277}, {"rect": [409, 317, 4, 5], "labels": [99], "size": 20}, {"rect": [19, 318, 5, 9], "labels": [100], "size": 43}, {"rect": [397, 320, 9, 14], "labels": [101], "size": 68}, {"rect": [406, 320, 9, 19], "labels": [102], "size": 100}, {"rect": [161, 322, 19, 15], "labels": [103], "size": 189}, {"rect": [113, 326, 0, 64], "labels": [104], "size": 65}, {"rect": [148, 329, 4, 8], "labels": [105], "size": 39}, {"rect": [162, 329, 5, 5], "labels": [106], "size": 24}, {"rect": [278, 329, 52, 40], "labels": [107], "size": 738}, {"rect": [33, 341, 15, 10], "labels": [108], "size": 28}, {"rect": [162, 341, 7, 4], "labels": [109], "size": 29}, {"rect": [397, 346, 5, 8], "labels": [110], "size": 24}, {"rect": [0, 350, 41, 27], "labels": [111], "size": 273}, {"rect": [195, 356, 28, 59], "labels": [112], "size": 120}, {"rect": [66, 358, 6, 7], "labels": [113], "size": 41}, {"rect": [139, 359, 7, 9], "labels": [114], "size": 36}, {"rect": [30, 360, 7, 4], "labels": [115], "size": 26}, {"rect": [76, 360, 21, 55], "labels": [116], "size": 167}, {"rect": [42, 366, 7, 10], "labels": [117], "size": 44}, {"rect": [61, 367, 5, 6], "labels": [118], "size": 31}, {"rect": [158, 367, 13, 14], "labels": [119], "size": 73}, {"rect": [399, 380, 6, 6], "labels": [120], "size": 37}, {"rect": [0, 381, 8, 6], "labels": [121], "size": 42}, {"rect": [27, 385, 10, 7], "labels": [122], "size": 46}, {"rect": [394, 390, 5, 5], "labels": [123], "size": 26}, {"rect": [181, 392, 7, 23], "labels": [124], "size": 29}, {"rect": [111, 397, 5, 18], "labels": [125], "size": 66}, {"rect": [46, 401, 7, 11], "labels": [126], "size": 54}, {"rect": [190, 407, 25, 8], "labels": [127], "size": 154}, {"rect": [18, 411, 9, 4], "labels": [128], "size": 43}, {"rect": [44, 413, 12, 2], "labels": [129], "size": 34}, {"rect": [59, 413, 11, 2], "labels": [130], "size": 30}, {"rect": [177, 41, 6, 28], "labels": [19, 26], "size": 99}, {"rect": [176, 32, 7, 37], "labels": [19, 26, 14], "size": 133}, {"rect": [399, 273, 16, 22], "labels": [83, 89], "size": 84}, {"rect": [285, 97, 12, 17], "labels": [34, 36], "size": 83}, {"rect": [170, 62, 5, 71], "labels": [27, 37], "size": 162}, {"rect": [137, 107, 32, 49], "labels": [41, 45], "size": 147}, {"rect": [159, 303, 24, 34], "labels": [95, 103], "size": 319}, {"rect": [190, 356, 33, 59], "labels": [112, 127], "size": 274}, {"rect": [159, 303, 24, 34], "labels": [95, 103, 106], "size": 343}, {"rect": [291, 35, 82, 37], "labels": [15, 21], "size": 438}, {"rect": [119, 141, 43, 47], "labels": [46, 55], "size": 470}, {"rect": [291, 35, 90, 37], "labels": [15, 21, 22], "size": 733}, {"rect": [0, 350, 41, 27], "labels": [111, 115], "size": 299}, {"rect": [0, 341, 48, 36], "labels": [111, 115, 108], "size": 327}, {"rect": [181, 44, 24, 75], "labels": [20, 30], "size": 480}, {"rect": [181, 44, 24, 75], "labels": [20, 30, 25], "size": 524}, {"rect": [119, 107, 50, 81], "labels": [46, 55, 41, 45], "size": 617}, {"rect": [178, 0, 33, 35], "labels": [4, 5], "size": 627}, {"rect": [176, 0, 35, 69], "labels": [4, 5, 19, 26, 14], "size": 760}, {"rect": [138, 290, 49, 63], "labels": [95, 103, 106, 91], "size": 1449}, {"rect": [138, 290, 49, 63], "labels": [95, 103, 106, 91, 105], "size": 1488}, {"rect": [138, 290, 49, 63], "labels": [95, 103, 106, 91, 105, 97], "size": 1526}, {"rect": [132, 290, 55, 63], "labels": [95, 103, 106, 91, 105, 97, 92], "size": 1571}, {"rect": [132, 290, 55, 63], "labels": [95, 103, 106, 91, 105, 97, 92, 109], "size": 1600}, {"rect": [132, 290, 55, 63], "labels": [95, 103, 106, 91, 105, 97, 92, 109, 94], "size": 1627}, {"rect": [18, 143, 60, 61], "labels": [47, 54], "size": 1323}, {"rect": [321, 74, 80, 145], "labels": [31, 38], "size": 1123}, {"rect": [321, 74, 80, 145], "labels": [31, 38, 48], "size": 1149}, {"rect": [321, 74, 94, 158], "labels": [31, 38, 48, 63], "size": 1217}, {"rect": [129, 210, 58, 143], "labels": [95, 103, 106, 91, 105, 97, 92, 109, 94, 64], "size": 3738}, {"rect": [129, 210, 58, 143], "labels": [95, 103, 106, 91, 105, 97, 92, 109, 94, 64, 86], "size": 3852}, {"rect": [129, 210, 58, 143], "labels": [95, 103, 106, 91, 105, 97, 92, 109, 94, 64, 86, 78], "size": 3924}, {"rect": [129, 210, 58, 143], "labels": [95, 103, 106, 91, 105, 97, 92, 109, 94, 64, 86, 78, 66], "size": 3996}, {"rect": [125, 210, 62, 143], "labels": [95, 103, 106, 91, 105, 97, 92, 109, 94, 64, 86, 78, 66, 75], "size": 4060}, {"rect": [119, 210, 68, 143], "labels": [95, 103, 106, 91, 105, 97, 92, 109, 94, 64, 86, 78, 66, 75, 69], "size": 4139}, {"rect": [119, 210, 68, 143], "labels": [95, 103, 106, 91, 105, 97, 92, 109, 94, 64, 86, 78, 66, 75, 69, 70], "size": 4161}, {"rect": [119, 205, 68, 148], "labels": [95, 103, 106, 91, 105, 97, 92, 109, 94, 64, 86, 78, 66, 75, 69, 70, 60], "size": 4188}, {"rect": [119, 205, 68, 148], "labels": [95, 103, 106, 91, 105, 97, 92, 109, 94, 64, 86, 78, 66, 75, 69, 70, 60, 65], "size": 4208}, {"rect": [396, 207, 19, 132], "labels": [62, 102], "size": 1978}, {"rect": [383, 207, 32, 208], "labels": [62, 102, 98], "size": 4255}, {"rect": [321, 74, 94, 341], "labels": [62, 102, 98, 31, 38, 48, 63], "size": 5472}, {"rect": [321, 74, 94, 341], "labels": [62, 102, 98, 31, 38, 48, 63, 101], "size": 5540}, {"rect": [321, 74, 94, 341], "labels": [62, 102, 98, 31, 38, 48, 63, 101, 83, 89], "size": 5624}, {"rect": [321, 74, 94, 341], "labels": [62, 102, 98, 31, 38, 48, 63, 101, 83, 89, 120], "size": 5661}, {"rect": [321, 74, 94, 341], "labels": [62, 102, 98, 31, 38, 48, 63, 101, 83, 89, 120, 123], "size": 5687}, {"rect": [321, 74, 94, 341], "labels": [62, 102, 98, 31, 38, 48, 63, 101, 83, 89, 120, 123, 110], "size": 5711}, {"rect": [293, 40, 122, 375], "labels": [62, 102, 98, 31, 38, 48, 63, 101, 83, 89, 120, 123, 110, 18], "size": 9391}, {"rect": [291, 35, 124, 380], "labels": [62, 102, 98, 31, 38, 48, 63, 101, 83, 89, 120, 123, 110, 18, 15, 21, 22], "size": 10124}, {"rect": [291, 35, 124, 380], "labels": [62, 102, 98, 31, 38, 48, 63, 101, 83, 89, 120, 123, 110, 18, 15, 21, 22, 32], "size": 10210}, {"rect": [285, 35, 130, 380], "labels": [62, 102, 98, 31, 38, 48, 63, 101, 83, 89, 120, 123, 110, 18, 15, 21, 22, 32, 34, 36], "size": 10293}, {"rect": [0, 29, 78, 196], "labels": [47, 54, 13], "size": 5430}, {"rect": [0, 0, 78, 225], "labels": [47, 54, 13, 2], "size": 5764}, {"rect": [0, 0, 78, 225], "labels": [47, 54, 13, 2, 52], "size": 5821}, {"rect": [0, 0, 78, 225], "labels": [47, 54, 13, 2, 52, 61], "size": 5880}, {"rect": [0, 0, 78, 225], "labels": [47, 54, 13, 2, 52, 61, 33], "size": 5923}, {"rect": [0, 0, 78, 225], "labels": [47, 54, 13, 2, 52, 61, 33, 67], "size": 5946}, {"rect": [49, 256, 172, 159], "labels": [77, 96], "size": 12543}, {"rect": [285, 35, 130, 380], "labels": [62, 102, 98, 31, 38, 48, 63, 101, 83, 89, 120, 123, 110, 18, 15, 21, 22, 32, 34, 36, 99], "size": 10313}, {"rect": [49, 205, 172, 210], "labels": [77, 96, 95, 103, 106, 91, 105, 97, 92, 109, 94, 64, 86, 78, 66, 75, 69, 70, 60, 65], "size": 16751}, {"rect": [49, 205, 172, 210], "labels": [77, 96, 95, 103, 106, 91, 105, 97, 92, 109, 94, 64, 86, 78, 66, 75, 69, 70, 60, 65, 116], "size": 16918}, {"rect": [49, 205, 172, 210], "labels": [77, 96, 95, 103, 106, 91, 105, 97, 92, 109, 94, 64, 86, 78, 66, 75, 69, 70, 60, 65, 116, 90], "size": 17067}, {"rect": [49, 205, 174, 210], "labels": [77, 96, 95, 103, 106, 91, 105, 97, 92, 109, 94, 64, 86, 78, 66, 75, 69, 70, 60, 65, 116, 90, 112, 127], "size": 17341}, {"rect": [49, 205, 174, 210], "labels": [77, 96, 95, 103, 106, 91, 105, 97, 92, 109, 94, 64, 86, 78, 66, 75, 69, 70, 60, 65, 116, 90, 112, 127, 119], "size": 17414}, {"rect": [49, 205, 174, 210], "labels": [77, 96, 95, 103, 106, 91, 105, 97, 92, 109, 94, 64, 86, 78, 66, 75, 69, 70, 60, 65, 116, 90, 112, 127, 119, 125], "size": 17480}, {"rect": [49, 205, 174, 210], "labels": [77, 96, 95, 103, 106, 91, 105, 97, 92, 109, 94, 64, 86, 78, 66, 75, 69, 70, 60, 65, 116, 90, 112, 127, 119, 125, 104], "size": 17545}, {"rect": [49, 205, 174, 210], "labels": [77, 96, 95, 103, 106, 91, 105, 97, 92, 109, 94, 64, 86, 78, 66, 75, 69, 70, 60, 65, 116, 90, 112, 127, 119, 125, 104, 88], "size": 17597}, {"rect": [49, 205, 174, 210], "labels": [77, 96, 95, 103, 106, 91, 105, 97, 92, 109, 94, 64, 86, 78, 66, 75, 69, 70, 60, 65, 116, 90, 112, 127, 119, 125, 104, 88, 113], "size": 17638}, {"rect": [49, 205, 174, 210], "labels": [77, 96, 95, 103, 106, 91, 105, 97, 92, 109, 94, 64, 86, 78, 66, 75, 69, 70, 60, 65, 116, 90, 112, 127, 119, 125, 104, 88, 113, 114], "size": 17674}, {"rect": [49, 205, 174, 210], "labels": [77, 96, 95, 103, 106, 91, 105, 97, 92, 109, 94, 64, 86, 78, 66, 75, 69, 70, 60, 65, 116, 90, 112, 127, 119, 125, 104, 88, 113, 114, 130], "size": 17704}, {"rect": [49, 205, 174, 210], "labels": [77, 96, 95, 103, 106, 91, 105, 97, 92, 109, 94, 64, 86, 78, 66, 75, 69, 70, 60, 65, 116, 90, 112, 127, 119, 125, 104, 88, 113, 114, 130, 124], "size": 17733}, {"rect": [49, 205, 174, 210], "labels": [77, 96, 95, 103, 106, 91, 105, 97, 92, 109, 94, 64, 86, 78, 66, 75, 69, 70, 60, 65, 116, 90, 112, 127, 119, 125, 104, 88, 113, 114, 130, 124, 118], "size": 17764}, {"rect": [46, 205, 177, 210], "labels": [77, 96, 95, 103, 106, 91, 105, 97, 92, 109, 94, 64, 86, 78, 66, 75, 69, 70, 60, 65, 116, 90, 112, 127, 119, 125, 104, 88, 113, 114, 130, 124, 118, 126], "size": 17818}, {"rect": [46, 205, 177, 210], "labels": [77, 96, 95, 103, 106, 91, 105, 97, 92, 109, 94, 64, 86, 78, 66, 75, 69, 70, 60, 65, 116, 90, 112, 127, 119, 125, 104, 88, 113, 114, 130, 124, 118, 126, 82], "size": 17841}, {"rect": [44, 205, 179, 210], "labels": [77, 96, 95, 103, 106, 91, 105, 97, 92, 109, 94, 64, 86, 78, 66, 75, 69, 70, 60, 65, 116, 90, 112, 127, 119, 125, 104, 88, 113, 114, 130, 124, 118, 126, 82, 129], "size": 17875}, {"rect": [211, 0, 204, 415], "labels": [62, 102, 98, 31, 38, 48, 63, 101, 83, 89, 120, 123, 110, 18, 15, 21, 22, 32, 34, 36, 99, 7], "size": 24973}, {"rect": [187, 0, 228, 415], "labels": [62, 102, 98, 31, 38, 48, 63, 101, 83, 89, 120, 123, 110, 18, 15, 21, 22, 32, 34, 36, 99, 7, 43], "size": 25733}, {"rect": [187, 0, 228, 415], "labels": [62, 102, 98, 31, 38, 48, 63, 101, 83, 89, 120, 123, 110, 18, 15, 21, 22, 32, 34, 36, 99, 7, 43, 53], "size": 26140}, {"rect": [187, 0, 228, 415], "labels": [62, 102, 98, 31, 38, 48, 63, 101, 83, 89, 120, 123, 110, 18, 15, 21, 22, 32, 34, 36, 99, 7, 43, 53, 49], "size": 26524}, {"rect": [187, 0, 228, 415], "labels": [62, 102, 98, 31, 38, 48, 63, 101, 83, 89, 120, 123, 110, 18, 15, 21, 22, 32, 34, 36, 99, 7, 43, 53, 49, 68], "size": 27652}, {"rect": [187, 0, 228, 415], "labels": [62, 102, 98, 31, 38, 48, 63, 101, 83, 89, 120, 123, 110, 18, 15, 21, 22, 32, 34, 36, 99, 7, 43, 53, 49, 68, 28], "size": 27836}, {"rect": [187, 0, 228, 415], "labels": [62, 102, 98, 31, 38, 48, 63, 101, 83, 89, 120, 123, 110, 18, 15, 21, 22, 32, 34, 36, 99, 7, 43, 53, 49, 68, 28, 24], "size": 27960}, {"rect": [187, 0, 228, 415], "labels": [62, 102, 98, 31, 38, 48, 63, 101, 83, 89, 120, 123, 110, 18, 15, 21, 22, 32, 34, 36, 99, 7, 43, 53, 49, 68, 28, 24, 40], "size": 28041}, {"rect": [187, 0, 228, 415], "labels": [62, 102, 98, 31, 38, 48, 63, 101, 83, 89, 120, 123, 110, 18, 15, 21, 22, 32, 34, 36, 99, 7, 43, 53, 49, 68, 28, 24, 40, 8], "size": 28092}, {"rect": [187, 0, 228, 415], "labels": [62, 102, 98, 31, 38, 48, 63, 101, 83, 89, 120, 123, 110, 18, 15, 21, 22, 32, 34, 36, 99, 7, 43, 53, 49, 68, 28, 24, 40, 8, 16], "size": 28122}, {"rect": [187, 0, 228, 415], "labels": [62, 102, 98, 31, 38, 48, 63, 101, 83, 89, 120, 123, 110, 18, 15, 21, 22, 32, 34, 36, 99, 7, 43, 53, 49, 68, 28, 24, 40, 8, 16, 10], "size": 28145}, {"rect": [187, 0, 228, 415], "labels": [62, 102, 98, 31, 38, 48, 63, 101, 83, 89, 120, 123, 110, 18, 15, 21, 22, 32, 34, 36, 99, 7, 43, 53, 49, 68, 28, 24, 40, 8, 16, 10, 42], "size": 28167}, {"rect": [187, 0, 228, 415], "labels": [62, 102, 98, 31, 38, 48, 63, 101, 83, 89, 120, 123, 110, 18, 15, 21, 22, 32, 34, 36, 99, 7, 43, 53, 49, 68, 28, 24, 40, 8, 16, 10, 42, 9], "size": 28195}, {"rect": [0, 0, 179, 225], "labels": [47, 54, 13, 2, 52, 61, 33, 67, 0], "size": 29007}, {"rect": [0, 0, 211, 225], "labels": [47, 54, 13, 2, 52, 61, 33, 67, 0, 4, 5, 19, 26, 14], "size": 29767}, {"rect": [0, 0, 211, 225], "labels": [47, 54, 13, 2, 52, 61, 33, 67, 0, 4, 5, 19, 26, 14, 35], "size": 30017}, {"rect": [0, 0, 211, 225], "labels": [47, 54, 13, 2, 52, 61, 33, 67, 0, 4, 5, 19, 26, 14, 35, 46, 55, 41, 45], "size": 30634}, {"rect": [0, 0, 211, 225], "labels": [47, 54, 13, 2, 52, 61, 33, 67, 0, 4, 5, 19, 26, 14, 35, 46, 55, 41, 45, 29], "size": 30765}, {"rect": [0, 0, 211, 225], "labels": [47, 54, 13, 2, 52, 61, 33, 67, 0, 4, 5, 19, 26, 14, 35, 46, 55, 41, 45, 29, 1], "size": 30873}, {"rect": [0, 0, 211, 225], "labels": [47, 54, 13, 2, 52, 61, 33, 67, 0, 4, 5, 19, 26, 14, 35, 46, 55, 41, 45, 29, 1, 27, 37], "size": 31035}, {"rect": [0, 0, 211, 225], "labels": [47, 54, 13, 2, 52, 61, 33, 67, 0, 4, 5, 19, 26, 14, 35, 46, 55, 41, 45, 29, 1, 27, 37, 44], "size": 31113}, {"rect": [0, 0, 211, 225], "labels": [47, 54, 13, 2, 52, 61, 33, 67, 0, 4, 5, 19, 26, 14, 35, 46, 55, 41, 45, 29, 1, 27, 37, 44, 51], "size": 31166}, {"rect": [0, 0, 211, 225], "labels": [47, 54, 13, 2, 52, 61, 33, 67, 0, 4, 5, 19, 26, 14, 35, 46, 55, 41, 45, 29, 1, 27, 37, 44, 51, 3], "size": 31198}, {"rect": [0, 0, 211, 225], "labels": [47, 54, 13, 2, 52, 61, 33, 67, 0, 4, 5, 19, 26, 14, 35, 46, 55, 41, 45, 29, 1, 27, 37, 44, 51, 3, 12], "size": 31226}, {"rect": [0, 0, 211, 225], "labels": [47, 54, 13, 2, 52, 61, 33, 67, 0, 4, 5, 19, 26, 14, 35, 46, 55, 41, 45, 29, 1, 27, 37, 44, 51, 3, 12, 11], "size": 31252}, {"rect": [0, 0, 211, 225], "labels": [47, 54, 13, 2, 52, 61, 33, 67, 0, 4, 5, 19, 26, 14, 35, 46, 55, 41, 45, 29, 1, 27, 37, 44, 51, 3, 12, 11, 39], "size": 31275}, {"rect": [0, 0, 211, 225], "labels": [47, 54, 13, 2, 52, 61, 33, 67, 0, 4, 5, 19, 26, 14, 35, 46, 55, 41, 45, 29, 1, 27, 37, 44, 51, 3, 12, 11, 39, 50], "size": 31297}, {"rect": [0, 0, 211, 225], "labels": [47, 54, 13, 2, 52, 61, 33, 67, 0, 4, 5, 19, 26, 14, 35, 46, 55, 41, 45, 29, 1, 27, 37, 44, 51, 3, 12, 11, 39, 50, 23], "size": 31334}, {"rect": [0, 0, 345, 415], "labels": [47, 54, 13, 2, 52, 61, 33, 67, 0, 4, 5, 19, 26, 14, 35, 46, 55, 41, 45, 29, 1, 27, 37, 44, 51, 3, 12, 11, 39, 50, 23, 6], "size": 67929}, {"rect": [0, 0, 415, 415], "labels": [47, 54, 13, 2, 52, 61, 33, 67, 0, 4, 5, 19, 26, 14, 35, 46, 55, 41, 45, 29, 1, 27, 37, 44, 51, 3, 12, 11, 39, 50, 23, 6, 62, 102, 98, 31, 38, 48, 63, 101, 83, 89, 120, 123, 110, 18, 15, 21, 22, 32, 34, 36, 99, 7, 43, 53, 49, 68, 28, 24, 40, 8, 16, 10, 42, 9], "size": 96124}, {"rect": [0, 0, 415, 415], "labels": [47, 54, 13, 2, 52, 61, 33, 67, 0, 4, 5, 19, 26, 14, 35, 46, 55, 41, 45, 29, 1, 27, 37, 44, 51, 3, 12, 11, 39, 50, 23, 6, 62, 102, 98, 31, 38, 48, 63, 101, 83, 89, 120, 123, 110, 18, 15, 21, 22, 32, 34, 36, 99, 7, 43, 53, 49, 68, 28, 24, 40, 8, 16, 10, 42, 9, 77, 96, 95, 103, 106, 91, 105, 97, 92, 109, 94, 64, 86, 78, 66, 75, 69, 70, 60, 65, 116, 90, 112, 127, 119, 125, 104, 88, 113, 114, 130, 124, 118, 126, 82, 129], "size": 113999}, {"rect": [0, 0, 415, 415], "labels": [47, 54, 13, 2, 52, 61, 33, 67, 0, 4, 5, 19, 26, 14, 35, 46, 55, 41, 45, 29, 1, 27, 37, 44, 51, 3, 12, 11, 39, 50, 23, 6, 62, 102, 98, 31, 38, 48, 63, 101, 83, 89, 120, 123, 110, 18, 15, 21, 22, 32, 34, 36, 99, 7, 43, 53, 49, 68, 28, 24, 40, 8, 16, 10, 42, 9, 77, 96, 95, 103, 106, 91, 105, 97, 92, 109, 94, 64, 86, 78, 66, 75, 69, 70, 60, 65, 116, 90, 112, 127, 119, 125, 104, 88, 113, 114, 130, 124, 118, 126, 82, 129, 107], "size": 114737}, {"rect": [0, 0, 415, 415], "labels": [47, 54, 13, 2, 52, 61, 33, 67, 0, 4, 5, 19, 26, 14, 35, 46, 55, 41, 45, 29, 1, 27, 37, 44, 51, 3, 12, 11, 39, 50, 23, 6, 62, 102, 98, 31, 38, 48, 63, 101, 83, 89, 120, 123, 110, 18, 15, 21, 22, 32, 34, 36, 99, 7, 43, 53, 49, 68, 28, 24, 40, 8, 16, 10, 42, 9, 77, 96, 95, 103, 106, 91, 105, 97, 92, 109, 94, 64, 86, 78, 66, 75, 69, 70, 60, 65, 116, 90, 112, 127, 119, 125, 104, 88, 113, 114, 130, 124, 118, 126, 82, 129, 107, 20, 30, 25], "size": 115261}, {"rect": [0, 0, 415, 415], "labels": [47, 54, 13, 2, 52, 61, 33, 67, 0, 4, 5, 19, 26, 14, 35, 46, 55, 41, 45, 29, 1, 27, 37, 44, 51, 3, 12, 11, 39, 50, 23, 6, 62, 102, 98, 31, 38, 48, 63, 101, 83, 89, 120, 123, 110, 18, 15, 21, 22, 32, 34, 36, 99, 7, 43, 53, 49, 68, 28, 24, 40, 8, 16, 10, 42, 9, 77, 96, 95, 103, 106, 91, 105, 97, 92, 109, 94, 64, 86, 78, 66, 75, 69, 70, 60, 65, 116, 90, 112, 127, 119, 125, 104, 88, 113, 114, 130, 124, 118, 126, 82, 129, 107, 20, 30, 25, 111, 115, 108], "size": 115588}, {"rect": [0, 0, 415, 415], "labels": [47, 54, 13, 2, 52, 61, 33, 67, 0, 4, 5, 19, 26, 14, 35, 46, 55, 41, 45, 29, 1, 27, 37, 44, 51, 3, 12, 11, 39, 50, 23, 6, 62, 102, 98, 31, 38, 48, 63, 101, 83, 89, 120, 123, 110, 18, 15, 21, 22, 32, 34, 36, 99, 7, 43, 53, 49, 68, 28, 24, 40, 8, 16, 10, 42, 9, 77, 96, 95, 103, 106, 91, 105, 97, 92, 109, 94, 64, 86, 78, 66, 75, 69, 70, 60, 65, 116, 90, 112, 127, 119, 125, 104, 88, 113, 114, 130, 124, 118, 126, 82, 129, 107, 20, 30, 25, 111, 115, 108, 71], "size": 115703}, {"rect": [0, 0, 415, 415], "labels": [47, 54, 13, 2, 52, 61, 33, 67, 0, 4, 5, 19, 26, 14, 35, 46, 55, 41, 45, 29, 1, 27, 37, 44, 51, 3, 12, 11, 39, 50, 23, 6, 62, 102, 98, 31, 38, 48, 63, 101, 83, 89, 120, 123, 110, 18, 15, 21, 22, 32, 34, 36, 99, 7, 43, 53, 49, 68, 28, 24, 40, 8, 16, 10, 42, 9, 77, 96, 95, 103, 106, 91, 105, 97, 92, 109, 94, 64, 86, 78, 66, 75, 69, 70, 60, 65, 116, 90, 112, 127, 119, 125, 104, 88, 113, 114, 130, 124, 118, 126, 82, 129, 107, 20, 30, 25, 111, 115, 108, 71, 59], "size": 115784}, {"rect": [0, 0, 415, 415], "labels": [47, 54, 13, 2, 52, 61, 33, 67, 0, 4, 5, 19, 26, 14, 35, 46, 55, 41, 45, 29, 1, 27, 37, 44, 51, 3, 12, 11, 39, 50, 23, 6, 62, 102, 98, 31, 38, 48, 63, 101, 83, 89, 120, 123, 110, 18, 15, 21, 22, 32, 34, 36, 99, 7, 43, 53, 49, 68, 28, 24, 40, 8, 16, 10, 42, 9, 77, 96, 95, 103, 106, 91, 105, 97, 92, 109, 94, 64, 86, 78, 66, 75, 69, 70, 60, 65, 116, 90, 112, 127, 119, 125, 104, 88, 113, 114, 130, 124, 118, 126, 82, 129, 107, 20, 30, 25, 111, 115, 108, 71, 59, 73], "size": 115848}, {"rect": [0, 0, 415, 415], "labels": [47, 54, 13, 2, 52, 61, 33, 67, 0, 4, 5, 19, 26, 14, 35, 46, 55, 41, 45, 29, 1, 27, 37, 44, 51, 3, 12, 11, 39, 50, 23, 6, 62, 102, 98, 31, 38, 48, 63, 101, 83, 89, 120, 123, 110, 18, 15, 21, 22, 32, 34, 36, 99, 7, 43, 53, 49, 68, 28, 24, 40, 8, 16, 10, 42, 9, 77, 96, 95, 103, 106, 91, 105, 97, 92, 109, 94, 64, 86, 78, 66, 75, 69, 70, 60, 65, 116, 90, 112, 127, 119, 125, 104, 88, 113, 114, 130, 124, 118, 126, 82, 129, 107, 20, 30, 25, 111, 115, 108, 71, 59, 73, 58], "size": 115902}, {"rect": [0, 0, 415, 415], "labels": [47, 54, 13, 2, 52, 61, 33, 67, 0, 4, 5, 19, 26, 14, 35, 46, 55, 41, 45, 29, 1, 27, 37, 44, 51, 3, 12, 11, 39, 50, 23, 6, 62, 102, 98, 31, 38, 48, 63, 101, 83, 89, 120, 123, 110, 18, 15, 21, 22, 32, 34, 36, 99, 7, 43, 53, 49, 68, 28, 24, 40, 8, 16, 10, 42, 9, 77, 96, 95, 103, 106, 91, 105, 97, 92, 109, 94, 64, 86, 78, 66, 75, 69, 70, 60, 65, 116, 90, 112, 127, 119, 125, 104, 88, 113, 114, 130, 124, 118, 126, 82, 129, 107, 20, 30, 25, 111, 115, 108, 71, 59, 73, 58, 122], "size": 115948}, {"rect": [0, 0, 415, 415], "labels": [47, 54, 13, 2, 52, 61, 33, 67, 0, 4, 5, 19, 26, 14, 35, 46, 55, 41, 45, 29, 1, 27, 37, 44, 51, 3, 12, 11, 39, 50, 23, 6, 62, 102, 98, 31, 38, 48, 63, 101, 83, 89, 120, 123, 110, 18, 15, 21, 22, 32, 34, 36, 99, 7, 43, 53, 49, 68, 28, 24, 40, 8, 16, 10, 42, 9, 77, 96, 95, 103, 106, 91, 105, 97, 92, 109, 94, 64, 86, 78, 66, 75, 69, 70, 60, 65, 116, 90, 112, 127, 119, 125, 104, 88, 113, 114, 130, 124, 118, 126, 82, 129, 107, 20, 30, 25, 111, 115, 108, 71, 59, 73, 58, 122, 57], "size": 115994}, {"rect": [0, 0, 415, 415], "labels": [47, 54, 13, 2, 52, 61, 33, 67, 0, 4, 5, 19, 26, 14, 35, 46, 55, 41, 45, 29, 1, 27, 37, 44, 51, 3, 12, 11, 39, 50, 23, 6, 62, 102, 98, 31, 38, 48, 63, 101, 83, 89, 120, 123, 110, 18, 15, 21, 22, 32, 34, 36, 99, 7, 43, 53, 49, 68, 28, 24, 40, 8, 16, 10, 42, 9, 77, 96, 95, 103, 106, 91, 105, 97, 92, 109, 94, 64, 86, 78, 66, 75, 69, 70, 60, 65, 116, 90, 112, 127, 119, 125, 104, 88, 113, 114, 130, 124, 118, 126, 82, 129, 107, 20, 30, 25, 111, 115, 108, 71, 59, 73, 58, 122, 57, 93], "size": 116040}, {"rect": [0, 0, 415, 415], "labels": [47, 54, 13, 2, 52, 61, 33, 67, 0, 4, 5, 19, 26, 14, 35, 46, 55, 41, 45, 29, 1, 27, 37, 44, 51, 3, 12, 11, 39, 50, 23, 6, 62, 102, 98, 31, 38, 48, 63, 101, 83, 89, 120, 123, 110, 18, 15, 21, 22, 32, 34, 36, 99, 7, 43, 53, 49, 68, 28, 24, 40, 8, 16, 10, 42, 9, 77, 96, 95, 103, 106, 91, 105, 97, 92, 109, 94, 64, 86, 78, 66, 75, 69, 70, 60, 65, 116, 90, 112, 127, 119, 125, 104, 88, 113, 114, 130, 124, 118, 126, 82, 129, 107, 20, 30, 25, 111, 115, 108, 71, 59, 73, 58, 122, 57, 93, 117], "size": 116084}, {"rect": [0, 0, 415, 415], "labels": [47, 54, 13, 2, 52, 61, 33, 67, 0, 4, 5, 19, 26, 14, 35, 46, 55, 41, 45, 29, 1, 27, 37, 44, 51, 3, 12, 11, 39, 50, 23, 6, 62, 102, 98, 31, 38, 48, 63, 101, 83, 89, 120, 123, 110, 18, 15, 21, 22, 32, 34, 36, 99, 7, 43, 53, 49, 68, 28, 24, 40, 8, 16, 10, 42, 9, 77, 96, 95, 103, 106, 91, 105, 97, 92, 109, 94, 64, 86, 78, 66, 75, 69, 70, 60, 65, 116, 90, 112, 127, 119, 125, 104, 88, 113, 114, 130, 124, 118, 126, 82, 129, 107, 20, 30, 25, 111, 115, 108, 71, 59, 73, 58, 122, 57, 93, 117, 128], "size": 116127}, {"rect": [0, 0, 415, 415], "labels": [47, 54, 13, 2, 52, 61, 33, 67, 0, 4, 5, 19, 26, 14, 35, 46, 55, 41, 45, 29, 1, 27, 37, 44, 51, 3, 12, 11, 39, 50, 23, 6, 62, 102, 98, 31, 38, 48, 63, 101, 83, 89, 120, 123, 110, 18, 15, 21, 22, 32, 34, 36, 99, 7, 43, 53, 49, 68, 28, 24, 40, 8, 16, 10, 42, 9, 77, 96, 95, 103, 106, 91, 105, 97, 92, 109, 94, 64, 86, 78, 66, 75, 69, 70, 60, 65, 116, 90, 112, 127, 119, 125, 104, 88, 113, 114, 130, 124, 118, 126, 82, 129, 107, 20, 30, 25, 111, 115, 108, 71, 59, 73, 58, 122, 57, 93, 117, 128, 100], "size": 116170}, {"rect": [0, 0, 415, 415], "labels": [47, 54, 13, 2, 52, 61, 33, 67, 0, 4, 5, 19, 26, 14, 35, 46, 55, 41, 45, 29, 1, 27, 37, 44, 51, 3, 12, 11, 39, 50, 23, 6, 62, 102, 98, 31, 38, 48, 63, 101, 83, 89, 120, 123, 110, 18, 15, 21, 22, 32, 34, 36, 99, 7, 43, 53, 49, 68, 28, 24, 40, 8, 16, 10, 42, 9, 77, 96, 95, 103, 106, 91, 105, 97, 92, 109, 94, 64, 86, 78, 66, 75, 69, 70, 60, 65, 116, 90, 112, 127, 119, 125, 104, 88, 113, 114, 130, 124, 118, 126, 82, 129, 107, 20, 30, 25, 111, 115, 108, 71, 59, 73, 58, 122, 57, 93, 117, 128, 100, 84], "size": 116210}, {"rect": [0, 0, 415, 415], "labels": [47, 54, 13, 2, 52, 61, 33, 67, 0, 4, 5, 19, 26, 14, 35, 46, 55, 41, 45, 29, 1, 27, 37, 44, 51, 3, 12, 11, 39, 50, 23, 6, 62, 102, 98, 31, 38, 48, 63, 101, 83, 89, 120, 123, 110, 18, 15, 21, 22, 32, 34, 36, 99, 7, 43, 53, 49, 68, 28, 24, 40, 8, 16, 10, 42, 9, 77, 96, 95, 103, 106, 91, 105, 97, 92, 109, 94, 64, 86, 78, 66, 75, 69, 70, 60, 65, 116, 90, 112, 127, 119, 125, 104, 88, 113, 114, 130, 124, 118, 126, 82, 129, 107, 20, 30, 25, 111, 115, 108, 71, 59, 73, 58, 122, 57, 93, 117, 128, 100, 84, 79], "size": 116249}, {"rect": [0, 0, 415, 415], "labels": [47, 54, 13, 2, 52, 61, 33, 67, 0, 4, 5, 19, 26, 14, 35, 46, 55, 41, 45, 29, 1, 27, 37, 44, 51, 3, 12, 11, 39, 50, 23, 6, 62, 102, 98, 31, 38, 48, 63, 101, 83, 89, 120, 123, 110, 18, 15, 21, 22, 32, 34, 36, 99, 7, 43, 53, 49, 68, 28, 24, 40, 8, 16, 10, 42, 9, 77, 96, 95, 103, 106, 91, 105, 97, 92, 109, 94, 64, 86, 78, 66, 75, 69, 70, 60, 65, 116, 90, 112, 127, 119, 125, 104, 88, 113, 114, 130, 124, 118, 126, 82, 129, 107, 20, 30, 25, 111, 115, 108, 71, 59, 73, 58, 122, 57, 93, 117, 128, 100, 84, 79, 121], "size": 116291}, {"rect": [0, 0, 415, 415], "labels": [47, 54, 13, 2, 52, 61, 33, 67, 0, 4, 5, 19, 26, 14, 35, 46, 55, 41, 45, 29, 1, 27, 37, 44, 51, 3, 12, 11, 39, 50, 23, 6, 62, 102, 98, 31, 38, 48, 63, 101, 83, 89, 120, 123, 110, 18, 15, 21, 22, 32, 34, 36, 99, 7, 43, 53, 49, 68, 28, 24, 40, 8, 16, 10, 42, 9, 77, 96, 95, 103, 106, 91, 105, 97, 92, 109, 94, 64, 86, 78, 66, 75, 69, 70, 60, 65, 116, 90, 112, 127, 119, 125, 104, 88, 113, 114, 130, 124, 118, 126, 82, 129, 107, 20, 30, 25, 111, 115, 108, 71, 59, 73, 58, 122, 57, 93, 117, 128, 100, 84, 79, 121, 74], "size": 116330}, {"rect": [0, 0, 415, 415], "labels": [47, 54, 13, 2, 52, 61, 33, 67, 0, 4, 5, 19, 26, 14, 35, 46, 55, 41, 45, 29, 1, 27, 37, 44, 51, 3, 12, 11, 39, 50, 23, 6, 62, 102, 98, 31, 38, 48, 63, 101, 83, 89, 120, 123, 110, 18, 15, 21, 22, 32, 34, 36, 99, 7, 43, 53, 49, 68, 28, 24, 40, 8, 16, 10, 42, 9, 77, 96, 95, 103, 106, 91, 105, 97, 92, 109, 94, 64, 86, 78, 66, 75, 69, 70, 60, 65, 116, 90, 112, 127, 119, 125, 104, 88, 113, 114, 130, 124, 118, 126, 82, 129, 107, 20, 30, 25, 111, 115, 108, 71, 59, 73, 58, 122, 57, 93, 117, 128, 100, 84, 79, 121, 74, 72], "size": 116363}, {"rect": [0, 0, 415, 415], "labels": [47, 54, 13, 2, 52, 61, 33, 67, 0, 4, 5, 19, 26, 14, 35, 46, 55, 41, 45, 29, 1, 27, 37, 44, 51, 3, 12, 11, 39, 50, 23, 6, 62, 102, 98, 31, 38, 48, 63, 101, 83, 89, 120, 123, 110, 18, 15, 21, 22, 32, 34, 36, 99, 7, 43, 53, 49, 68, 28, 24, 40, 8, 16, 10, 42, 9, 77, 96, 95, 103, 106, 91, 105, 97, 92, 109, 94, 64, 86, 78, 66, 75, 69, 70, 60, 65, 116, 90, 112, 127, 119, 125, 104, 88, 113, 114, 130, 124, 118, 126, 82, 129, 107, 20, 30, 25, 111, 115, 108, 71, 59, 73, 58, 122, 57, 93, 117, 128, 100, 84, 79, 121, 74, 72, 85], "size": 116396}, {"rect": [0, 0, 415, 415], "labels": [47, 54, 13, 2, 52, 61, 33, 67, 0, 4, 5, 19, 26, 14, 35, 46, 55, 41, 45, 29, 1, 27, 37, 44, 51, 3, 12, 11, 39, 50, 23, 6, 62, 102, 98, 31, 38, 48, 63, 101, 83, 89, 120, 123, 110, 18, 15, 21, 22, 32, 34, 36, 99, 7, 43, 53, 49, 68, 28, 24, 40, 8, 16, 10, 42, 9, 77, 96, 95, 103, 106, 91, 105, 97, 92, 109, 94, 64, 86, 78, 66, 75, 69, 70, 60, 65, 116, 90, 112, 127, 119, 125, 104, 88, 113, 114, 130, 124, 118, 126, 82, 129, 107, 20, 30, 25, 111, 115, 108, 71, 59, 73, 58, 122, 57, 93, 117, 128, 100, 84, 79, 121, 74, 72, 85, 56], "size": 116429}, {"rect": [0, 0, 415, 415], "labels": [47, 54, 13, 2, 52, 61, 33, 67, 0, 4, 5, 19, 26, 14, 35, 46, 55, 41, 45, 29, 1, 27, 37, 44, 51, 3, 12, 11, 39, 50, 23, 6, 62, 102, 98, 31, 38, 48, 63, 101, 83, 89, 120, 123, 110, 18, 15, 21, 22, 32, 34, 36, 99, 7, 43, 53, 49, 68, 28, 24, 40, 8, 16, 10, 42, 9, 77, 96, 95, 103, 106, 91, 105, 97, 92, 109, 94, 64, 86, 78, 66, 75, 69, 70, 60, 65, 116, 90, 112, 127, 119, 125, 104, 88, 113, 114, 130, 124, 118, 126, 82, 129, 107, 20, 30, 25, 111, 115, 108, 71, 59, 73, 58, 122, 57, 93, 117, 128, 100, 84, 79, 121, 74, 72, 85, 56, 76], "size": 116460}, {"rect": [0, 0, 415, 415], "labels": [47, 54, 13, 2, 52, 61, 33, 67, 0, 4, 5, 19, 26, 14, 35, 46, 55, 41, 45, 29, 1, 27, 37, 44, 51, 3, 12, 11, 39, 50, 23, 6, 62, 102, 98, 31, 38, 48, 63, 101, 83, 89, 120, 123, 110, 18, 15, 21, 22, 32, 34, 36, 99, 7, 43, 53, 49, 68, 28, 24, 40, 8, 16, 10, 42, 9, 77, 96, 95, 103, 106, 91, 105, 97, 92, 109, 94, 64, 86, 78, 66, 75, 69, 70, 60, 65, 116, 90, 112, 127, 119, 125, 104, 88, 113, 114, 130, 124, 118, 126, 82, 129, 107, 20, 30, 25, 111, 115, 108, 71, 59, 73, 58, 122, 57, 93, 117, 128, 100, 84, 79, 121, 74, 72, 85, 56, 76, 80], "size": 116484}, {"rect": [0, 0, 415, 415], "labels": [47, 54, 13, 2, 52, 61, 33, 67, 0, 4, 5, 19, 26, 14, 35, 46, 55, 41, 45, 29, 1, 27, 37, 44, 51, 3, 12, 11, 39, 50, 23, 6, 62, 102, 98, 31, 38, 48, 63, 101, 83, 89, 120, 123, 110, 18, 15, 21, 22, 32, 34, 36, 99, 7, 43, 53, 49, 68, 28, 24, 40, 8, 16, 10, 42, 9, 77, 96, 95, 103, 106, 91, 105, 97, 92, 109, 94, 64, 86, 78, 66, 75, 69, 70, 60, 65, 116, 90, 112, 127, 119, 125, 104, 88, 113, 114, 130, 124, 118, 126, 82, 129, 107, 20, 30, 25, 111, 115, 108, 71, 59, 73, 58, 122, 57, 93, 117, 128, 100, 84, 79, 121, 74, 72, 85, 56, 76, 80, 87], "size": 116507}, {"rect": [0, 0, 415, 415], "labels": [47, 54, 13, 2, 52, 61, 33, 67, 0, 4, 5, 19, 26, 14, 35, 46, 55, 41, 45, 29, 1, 27, 37, 44, 51, 3, 12, 11, 39, 50, 23, 6, 62, 102, 98, 31, 38, 48, 63, 101, 83, 89, 120, 123, 110, 18, 15, 21, 22, 32, 34, 36, 99, 7, 43, 53, 49, 68, 28, 24, 40, 8, 16, 10, 42, 9, 77, 96, 95, 103, 106, 91, 105, 97, 92, 109, 94, 64, 86, 78, 66, 75, 69, 70, 60, 65, 116, 90, 112, 127, 119, 125, 104, 88, 113, 114, 130, 124, 118, 126, 82, 129, 107, 20, 30, 25, 111, 115, 108, 71, 59, 73, 58, 122, 57, 93, 117, 128, 100, 84, 79, 121, 74, 72, 85, 56, 76, 80, 87, 81], "size": 116532}, {"rect": [0, 0, 415, 415], "labels": [47, 54, 13, 2, 52, 61, 33, 67, 0, 4, 5, 19, 26, 14, 35, 46, 55, 41, 45, 29, 1, 27, 37, 44, 51, 3, 12, 11, 39, 50, 23, 6, 62, 102, 98, 31, 38, 48, 63, 101, 83, 89, 120, 123, 110, 18, 15, 21, 22, 32, 34, 36, 99, 7, 43, 53, 49, 68, 28, 24, 40, 8, 16, 10, 42, 9, 77, 96, 95, 103, 106, 91, 105, 97, 92, 109, 94, 64, 86, 78, 66, 75, 69, 70, 60, 65, 116, 90, 112, 127, 119, 125, 104, 88, 113, 114, 130, 124, 118, 126, 82, 129, 107, 20, 30, 25, 111, 115, 108, 71, 59, 73, 58, 122, 57, 93, 117, 128, 100, 84, 79, 121, 74, 72, 85, 56, 76, 80, 87, 81, 17], "size": 173056}]